[
  {
    "watch_org": "NVIDIA",
    "full_name": "NVIDIA/warp",
    "html_url": "https://github.com/NVIDIA/warp",
    "stargazers_count": 6758,
    "updated_at": "2026-06-15T06:01:34Z",
    "why": "recent update in watched organization `NVIDIA`"
  },
  {
    "watch_org": "NVIDIA",
    "full_name": "NVIDIA/flashdreams",
    "html_url": "https://github.com/NVIDIA/flashdreams",
    "stargazers_count": 326,
    "updated_at": "2026-06-15T05:32:47Z",
    "why": "recent update in watched organization `NVIDIA`"
  },
  {
    "watch_org": "NVIDIA",
    "full_name": "NVIDIA/GR00T-Dreams",
    "html_url": "https://github.com/NVIDIA/GR00T-Dreams",
    "stargazers_count": 571,
    "updated_at": "2026-06-15T04:12:39Z",
    "why": "recent update in watched organization `NVIDIA`"
  },
  {
    "watch_org": "NVIDIA",
    "full_name": "NVIDIA/DreamDojo",
    "html_url": "https://github.com/NVIDIA/DreamDojo",
    "stargazers_count": 935,
    "updated_at": "2026-06-15T03:20:34Z",
    "why": "recent update in watched organization `NVIDIA`"
  },
  {
    "watch_org": "NVIDIA",
    "full_name": "NVIDIA/Cosmos-Tokenizer",
    "html_url": "https://github.com/NVIDIA/Cosmos-Tokenizer",
    "stargazers_count": 1724,
    "updated_at": "2026-06-15T03:16:53Z",
    "why": "recent update in watched organization `NVIDIA`"
  },
  {
    "watch_org": "NVIDIA",
    "full_name": "NVIDIA/simready-foundation",
    "html_url": "https://github.com/NVIDIA/simready-foundation",
    "stargazers_count": 42,
    "updated_at": "2026-06-15T02:20:34Z",
    "why": "recent update in watched organization `NVIDIA`"
  },
  {
    "watch_org": "NVIDIA",
    "full_name": "NVIDIA/instant-nurec",
    "html_url": "https://github.com/NVIDIA/instant-nurec",
    "stargazers_count": 21,
    "updated_at": "2026-06-15T01:57:45Z",
    "why": "recent update in watched organization `NVIDIA`"
  },
  {
    "watch_org": "NVIDIA",
    "full_name": "NVIDIA/asset-harvester",
    "html_url": "https://github.com/NVIDIA/asset-harvester",
    "stargazers_count": 210,
    "updated_at": "2026-06-14T19:33:13Z",
    "why": "recent update in watched organization `NVIDIA`"
  },
  {
    "watch_org": "NVLabs",
    "full_name": "NVlabs/GRAIL",
    "html_url": "https://github.com/NVlabs/GRAIL",
    "stargazers_count": 298,
    "updated_at": "2026-06-15T06:31:59Z",
    "why": "recent update in watched organization `NVLabs`"
  },
  {
    "watch_org": "NVLabs",
    "full_name": "NVlabs/PointWorld",
    "html_url": "https://github.com/NVlabs/PointWorld",
    "stargazers_count": 412,
    "updated_at": "2026-06-15T06:28:56Z",
    "why": "recent update in watched organization `NVLabs`"
  },
  {
    "watch_org": "NVLabs",
    "full_name": "NVlabs/SpatialClaw",
    "html_url": "https://github.com/NVlabs/SpatialClaw",
    "stargazers_count": 75,
    "updated_at": "2026-06-15T06:21:55Z",
    "why": "recent update in watched organization `NVLabs`"
  },
  {
    "watch_org": "NVLabs",
    "full_name": "NVlabs/LongSplat",
    "html_url": "https://github.com/NVlabs/LongSplat",
    "stargazers_count": 789,
    "updated_at": "2026-06-15T06:19:14Z",
    "why": "recent update in watched organization `NVLabs`"
  },
  {
    "watch_org": "NVLabs",
    "full_name": "NVlabs/GEM-X",
    "html_url": "https://github.com/NVlabs/GEM-X",
    "stargazers_count": 323,
    "updated_at": "2026-06-15T06:11:27Z",
    "why": "recent update in watched organization `NVLabs`"
  },
  {
    "watch_org": "NVLabs",
    "full_name": "NVlabs/GraspGen",
    "html_url": "https://github.com/NVlabs/GraspGen",
    "stargazers_count": 485,
    "updated_at": "2026-06-15T05:32:33Z",
    "why": "recent update in watched organization `NVLabs`"
  },
  {
    "watch_org": "NVLabs",
    "full_name": "NVlabs/pointbridge",
    "html_url": "https://github.com/NVlabs/pointbridge",
    "stargazers_count": 19,
    "updated_at": "2026-06-15T05:27:39Z",
    "why": "recent update in watched organization `NVLabs`"
  },
  {
    "watch_org": "NVLabs",
    "full_name": "NVlabs/blade",
    "html_url": "https://github.com/NVlabs/blade",
    "stargazers_count": 51,
    "updated_at": "2026-06-15T04:43:18Z",
    "why": "recent update in watched organization `NVLabs`"
  },
  {
    "watch_org": "NVLabs",
    "full_name": "NVlabs/dexmimicgen",
    "html_url": "https://github.com/NVlabs/dexmimicgen",
    "stargazers_count": 254,
    "updated_at": "2026-06-15T04:01:21Z",
    "why": "recent update in watched organization `NVLabs`"
  },
  {
    "watch_org": "NVLabs",
    "full_name": "NVlabs/sage",
    "html_url": "https://github.com/NVlabs/sage",
    "stargazers_count": 325,
    "updated_at": "2026-06-15T03:52:33Z",
    "why": "recent update in watched organization `NVLabs`"
  },
  {
    "watch_org": "NVLabs",
    "full_name": "NVlabs/PixelDiT",
    "html_url": "https://github.com/NVlabs/PixelDiT",
    "stargazers_count": 796,
    "updated_at": "2026-06-15T03:47:08Z",
    "why": "recent update in watched organization `NVLabs`"
  },
  {
    "watch_org": "NVLabs",
    "full_name": "NVlabs/DiffiT",
    "html_url": "https://github.com/NVlabs/DiffiT",
    "stargazers_count": 518,
    "updated_at": "2026-06-15T02:19:20Z",
    "why": "recent update in watched organization `NVLabs`"
  },
  {
    "watch_org": "NVLabs",
    "full_name": "NVlabs/ProtoMotions",
    "html_url": "https://github.com/NVlabs/ProtoMotions",
    "stargazers_count": 1713,
    "updated_at": "2026-06-15T00:32:02Z",
    "why": "recent update in watched organization `NVLabs`"
  },
  {
    "watch_org": "NVLabs",
    "full_name": "NVlabs/instant-ngp",
    "html_url": "https://github.com/NVlabs/instant-ngp",
    "stargazers_count": 17436,
    "updated_at": "2026-06-15T00:30:24Z",
    "why": "recent update in watched organization `NVLabs`"
  },
  {
    "watch_org": "NVLabs",
    "full_name": "NVlabs/DiffusionNFT",
    "html_url": "https://github.com/NVlabs/DiffusionNFT",
    "stargazers_count": 901,
    "updated_at": "2026-06-14T16:32:50Z",
    "why": "recent update in watched organization `NVLabs`"
  },
  {
    "watch_org": "NVLabs",
    "full_name": "NVlabs/alpasim",
    "html_url": "https://github.com/NVlabs/alpasim",
    "stargazers_count": 1070,
    "updated_at": "2026-06-14T14:46:24Z",
    "why": "recent update in watched organization `NVLabs`"
  },
  {
    "watch_org": "NVLabs",
    "full_name": "NVlabs/mimicgen",
    "html_url": "https://github.com/NVlabs/mimicgen",
    "stargazers_count": 596,
    "updated_at": "2026-06-14T14:06:21Z",
    "why": "recent update in watched organization `NVLabs`"
  },
  {
    "watch_org": "NVLabs",
    "full_name": "NVlabs/FB-BEV",
    "html_url": "https://github.com/NVlabs/FB-BEV",
    "stargazers_count": 797,
    "updated_at": "2026-06-14T13:56:44Z",
    "why": "recent update in watched organization `NVLabs`"
  },
  {
    "watch_org": "NVLabs",
    "full_name": "NVlabs/PartPacker",
    "html_url": "https://github.com/NVlabs/PartPacker",
    "stargazers_count": 819,
    "updated_at": "2026-06-14T10:04:41Z",
    "why": "recent update in watched organization `NVLabs`"
  },
  {
    "watch_org": "NVLabs",
    "full_name": "NVlabs/edm",
    "html_url": "https://github.com/NVlabs/edm",
    "stargazers_count": 1967,
    "updated_at": "2026-06-14T09:02:28Z",
    "why": "recent update in watched organization `NVLabs`"
  },
  {
    "watch_org": "NVLabs",
    "full_name": "NVlabs/VoxFormer",
    "html_url": "https://github.com/NVlabs/VoxFormer",
    "stargazers_count": 1198,
    "updated_at": "2026-06-14T05:42:15Z",
    "why": "recent update in watched organization `NVLabs`"
  },
  {
    "watch_org": "NVLabs",
    "full_name": "NVlabs/Nemotron-Labs-Diffusion",
    "html_url": "https://github.com/NVlabs/Nemotron-Labs-Diffusion",
    "stargazers_count": 49,
    "updated_at": "2026-06-14T00:48:01Z",
    "why": "recent update in watched organization `NVLabs`"
  },
  {
    "watch_org": "NVLabs",
    "full_name": "NVlabs/GaussianSTORM",
    "html_url": "https://github.com/NVlabs/GaussianSTORM",
    "stargazers_count": 360,
    "updated_at": "2026-06-13T12:14:07Z",
    "why": "recent update in watched organization `NVLabs`"
  },
  {
    "watch_org": "NVLabs",
    "full_name": "NVlabs/neuralangelo",
    "html_url": "https://github.com/NVlabs/neuralangelo",
    "stargazers_count": 4598,
    "updated_at": "2026-06-13T10:51:08Z",
    "why": "recent update in watched organization `NVLabs`"
  },
  {
    "watch_org": "NVLabs",
    "full_name": "NVlabs/Fast-dLLM",
    "html_url": "https://github.com/NVlabs/Fast-dLLM",
    "stargazers_count": 1040,
    "updated_at": "2026-06-13T04:18:38Z",
    "why": "recent update in watched organization `NVLabs`"
  },
  {
    "watch_org": "NVLabs",
    "full_name": "NVlabs/WarpConvNet",
    "html_url": "https://github.com/NVlabs/WarpConvNet",
    "stargazers_count": 200,
    "updated_at": "2026-06-13T00:19:04Z",
    "why": "recent update in watched organization `NVLabs`"
  },
  {
    "watch_org": "NVLabs",
    "full_name": "NVlabs/AnyFlow",
    "html_url": "https://github.com/NVlabs/AnyFlow",
    "stargazers_count": 366,
    "updated_at": "2026-06-12T20:43:43Z",
    "why": "recent update in watched organization `NVLabs`"
  },
  {
    "watch_org": "Google Research",
    "full_name": "google-research/pix2seq",
    "html_url": "https://github.com/google-research/pix2seq",
    "stargazers_count": 944,
    "updated_at": "2026-06-15T00:32:14Z",
    "why": "recent update in watched organization `Google Research`"
  },
  {
    "watch_org": "Google Research",
    "full_name": "google-research/m2svid",
    "html_url": "https://github.com/google-research/m2svid",
    "stargazers_count": 28,
    "updated_at": "2026-06-13T06:40:46Z",
    "why": "recent update in watched organization `Google Research`"
  },
  {
    "watch_org": "Google Research",
    "full_name": "google-research/language-table",
    "html_url": "https://github.com/google-research/language-table",
    "stargazers_count": 360,
    "updated_at": "2026-06-13T01:00:03Z",
    "why": "recent update in watched organization `Google Research`"
  },
  {
    "watch_org": "Google Research",
    "full_name": "google-research/Splat-SLAM",
    "html_url": "https://github.com/google-research/Splat-SLAM",
    "stargazers_count": 355,
    "updated_at": "2026-06-12T06:34:57Z",
    "why": "recent update in watched organization `Google Research`"
  },
  {
    "watch_org": "Google Research",
    "full_name": "google-research/DBAP-simulation",
    "html_url": "https://github.com/google-research/DBAP-simulation",
    "stargazers_count": 2,
    "updated_at": "2026-06-11T12:50:50Z",
    "why": "recent update in watched organization `Google Research`"
  },
  {
    "watch_org": "Google Research",
    "full_name": "google-research/robel-scenes",
    "html_url": "https://github.com/google-research/robel-scenes",
    "stargazers_count": 14,
    "updated_at": "2026-06-11T12:50:49Z",
    "why": "recent update in watched organization `Google Research`"
  },
  {
    "watch_org": "Google Research",
    "full_name": "google-research/recsim",
    "html_url": "https://github.com/google-research/recsim",
    "stargazers_count": 786,
    "updated_at": "2026-06-11T12:50:48Z",
    "why": "recent update in watched organization `Google Research`"
  },
  {
    "watch_org": "Google Research",
    "full_name": "google-research/recsim_ng",
    "html_url": "https://github.com/google-research/recsim_ng",
    "stargazers_count": 127,
    "updated_at": "2026-06-11T12:50:48Z",
    "why": "recent update in watched organization `Google Research`"
  },
  {
    "watch_org": "Google Research",
    "full_name": "google-research/corenet",
    "html_url": "https://github.com/google-research/corenet",
    "stargazers_count": 122,
    "updated_at": "2026-06-08T19:42:57Z",
    "why": "recent update in watched organization `Google Research`"
  },
  {
    "watch_org": "Google Research",
    "full_name": "google-research/diffusion-score-smoothing",
    "html_url": "https://github.com/google-research/diffusion-score-smoothing",
    "stargazers_count": 5,
    "updated_at": "2026-06-08T19:42:25Z",
    "why": "recent update in watched organization `Google Research`"
  },
  {
    "watch_org": "Google Research",
    "full_name": "google-research/falken",
    "html_url": "https://github.com/google-research/falken",
    "stargazers_count": 272,
    "updated_at": "2026-06-08T19:41:22Z",
    "why": "recent update in watched organization `Google Research`"
  },
  {
    "watch_org": "Google DeepMind",
    "full_name": "google-deepmind/representations4d",
    "html_url": "https://github.com/google-deepmind/representations4d",
    "stargazers_count": 166,
    "updated_at": "2026-06-15T01:53:56Z",
    "why": "recent update in watched organization `Google DeepMind`"
  },
  {
    "watch_org": "Google DeepMind",
    "full_name": "google-deepmind/concordia",
    "html_url": "https://github.com/google-deepmind/concordia",
    "stargazers_count": 1478,
    "updated_at": "2026-06-14T17:33:41Z",
    "why": "recent update in watched organization `Google DeepMind`"
  },
  {
    "watch_org": "Google DeepMind",
    "full_name": "google-deepmind/dm_control",
    "html_url": "https://github.com/google-deepmind/dm_control",
    "stargazers_count": 4616,
    "updated_at": "2026-06-13T07:01:22Z",
    "why": "recent update in watched organization `Google DeepMind`"
  },
  {
    "watch_org": "Google DeepMind",
    "full_name": "google-deepmind/md4",
    "html_url": "https://github.com/google-deepmind/md4",
    "stargazers_count": 161,
    "updated_at": "2026-06-12T10:53:16Z",
    "why": "recent update in watched organization `Google DeepMind`"
  },
  {
    "watch_org": "Google DeepMind",
    "full_name": "google-deepmind/torax",
    "html_url": "https://github.com/google-deepmind/torax",
    "stargazers_count": 681,
    "updated_at": "2026-06-12T08:12:06Z",
    "why": "recent update in watched organization `Google DeepMind`"
  },
  {
    "watch_org": "Google DeepMind",
    "full_name": "google-deepmind/lab",
    "html_url": "https://github.com/google-deepmind/lab",
    "stargazers_count": 7365,
    "updated_at": "2026-06-12T00:24:40Z",
    "why": "recent update in watched organization `Google DeepMind`"
  },
  {
    "watch_org": "Google DeepMind",
    "full_name": "google-deepmind/kinetics-i3d",
    "html_url": "https://github.com/google-deepmind/kinetics-i3d",
    "stargazers_count": 1836,
    "updated_at": "2026-06-11T16:28:52Z",
    "why": "recent update in watched organization `Google DeepMind`"
  },
  {
    "watch_org": "Google DeepMind",
    "full_name": "google-deepmind/simulation_streams",
    "html_url": "https://github.com/google-deepmind/simulation_streams",
    "stargazers_count": 27,
    "updated_at": "2026-06-11T15:48:20Z",
    "why": "recent update in watched organization `Google DeepMind`"
  },
  {
    "watch_org": "Tencent",
    "full_name": "Tencent/xLua",
    "html_url": "https://github.com/Tencent/xLua",
    "stargazers_count": 10099,
    "updated_at": "2026-06-15T06:34:53Z",
    "why": "recent update in watched organization `Tencent`"
  },
  {
    "watch_org": "Tencent",
    "full_name": "Tencent/MedicalNet",
    "html_url": "https://github.com/Tencent/MedicalNet",
    "stargazers_count": 2234,
    "updated_at": "2026-06-15T06:22:26Z",
    "why": "recent update in watched organization `Tencent`"
  },
  {
    "watch_org": "Tencent",
    "full_name": "Tencent/loli_profiler",
    "html_url": "https://github.com/Tencent/loli_profiler",
    "stargazers_count": 688,
    "updated_at": "2026-06-15T04:22:20Z",
    "why": "recent update in watched organization `Tencent`"
  },
  {
    "watch_org": "Tencent",
    "full_name": "Tencent/AngelSlim",
    "html_url": "https://github.com/Tencent/AngelSlim",
    "stargazers_count": 1309,
    "updated_at": "2026-06-15T04:12:08Z",
    "why": "recent update in watched organization `Tencent`"
  },
  {
    "watch_org": "Tencent",
    "full_name": "Tencent/MimicMotion",
    "html_url": "https://github.com/Tencent/MimicMotion",
    "stargazers_count": 2603,
    "updated_at": "2026-06-14T17:32:54Z",
    "why": "recent update in watched organization `Tencent`"
  },
  {
    "watch_org": "Tencent",
    "full_name": "Tencent/APIJSON",
    "html_url": "https://github.com/Tencent/APIJSON",
    "stargazers_count": 18391,
    "updated_at": "2026-06-14T11:30:11Z",
    "why": "recent update in watched organization `Tencent`"
  },
  {
    "watch_org": "Tencent",
    "full_name": "Tencent/WeDLM",
    "html_url": "https://github.com/Tencent/WeDLM",
    "stargazers_count": 643,
    "updated_at": "2026-06-12T00:45:52Z",
    "why": "recent update in watched organization `Tencent`"
  },
  {
    "watch_org": "Tencent",
    "full_name": "Tencent/KsanaDiT",
    "html_url": "https://github.com/Tencent/KsanaDiT",
    "stargazers_count": 55,
    "updated_at": "2026-06-11T08:54:38Z",
    "why": "recent update in watched organization `Tencent`"
  },
  {
    "watch_org": "Tencent Hunyuan",
    "full_name": "Tencent-Hunyuan/DisCa",
    "html_url": "https://github.com/Tencent-Hunyuan/DisCa",
    "stargazers_count": 22,
    "updated_at": "2026-06-15T06:25:53Z",
    "why": "recent update in watched organization `Tencent Hunyuan`"
  },
  {
    "watch_org": "Tencent Hunyuan",
    "full_name": "Tencent-Hunyuan/OmniWeaving",
    "html_url": "https://github.com/Tencent-Hunyuan/OmniWeaving",
    "stargazers_count": 881,
    "updated_at": "2026-06-15T03:51:18Z",
    "why": "recent update in watched organization `Tencent Hunyuan`"
  },
  {
    "watch_org": "Tencent Hunyuan",
    "full_name": "Tencent-Hunyuan/HunyuanVideo-Foley",
    "html_url": "https://github.com/Tencent-Hunyuan/HunyuanVideo-Foley",
    "stargazers_count": 1044,
    "updated_at": "2026-06-14T22:37:27Z",
    "why": "recent update in watched organization `Tencent Hunyuan`"
  },
  {
    "watch_org": "Tencent Hunyuan",
    "full_name": "Tencent-Hunyuan/HY-Motion-1.0",
    "html_url": "https://github.com/Tencent-Hunyuan/HY-Motion-1.0",
    "stargazers_count": 2394,
    "updated_at": "2026-06-14T20:14:48Z",
    "why": "recent update in watched organization `Tencent Hunyuan`"
  },
  {
    "watch_org": "Tencent Hunyuan",
    "full_name": "Tencent-Hunyuan/Hunyuan3D-Omni",
    "html_url": "https://github.com/Tencent-Hunyuan/Hunyuan3D-Omni",
    "stargazers_count": 588,
    "updated_at": "2026-06-14T19:33:00Z",
    "why": "recent update in watched organization `Tencent Hunyuan`"
  },
  {
    "watch_org": "Tencent Hunyuan",
    "full_name": "Tencent-Hunyuan/HY-World-2.0",
    "html_url": "https://github.com/Tencent-Hunyuan/HY-World-2.0",
    "stargazers_count": 2222,
    "updated_at": "2026-06-14T16:59:32Z",
    "why": "recent update in watched organization `Tencent Hunyuan`"
  },
  {
    "watch_org": "Tencent Hunyuan",
    "full_name": "Tencent-Hunyuan/HunyuanDiT",
    "html_url": "https://github.com/Tencent-Hunyuan/HunyuanDiT",
    "stargazers_count": 4290,
    "updated_at": "2026-06-14T02:32:34Z",
    "why": "recent update in watched organization `Tencent Hunyuan`"
  },
  {
    "watch_org": "Tencent Hunyuan",
    "full_name": "Tencent-Hunyuan/MixGRPO",
    "html_url": "https://github.com/Tencent-Hunyuan/MixGRPO",
    "stargazers_count": 1140,
    "updated_at": "2026-06-14T00:38:30Z",
    "why": "recent update in watched organization `Tencent Hunyuan`"
  },
  {
    "watch_org": "Tencent Hunyuan",
    "full_name": "Tencent-Hunyuan/HunyuanWorld-Mirror",
    "html_url": "https://github.com/Tencent-Hunyuan/HunyuanWorld-Mirror",
    "stargazers_count": 1140,
    "updated_at": "2026-06-13T17:24:51Z",
    "why": "recent update in watched organization `Tencent Hunyuan`"
  },
  {
    "watch_org": "Tencent Hunyuan",
    "full_name": "Tencent-Hunyuan/HunyuanVideo-Avatar",
    "html_url": "https://github.com/Tencent-Hunyuan/HunyuanVideo-Avatar",
    "stargazers_count": 2117,
    "updated_at": "2026-06-13T02:34:20Z",
    "why": "recent update in watched organization `Tencent Hunyuan`"
  },
  {
    "watch_org": "Tencent Hunyuan",
    "full_name": "Tencent-Hunyuan/SAGE-GRPO",
    "html_url": "https://github.com/Tencent-Hunyuan/SAGE-GRPO",
    "stargazers_count": 124,
    "updated_at": "2026-06-12T20:29:39Z",
    "why": "recent update in watched organization `Tencent Hunyuan`"
  },
  {
    "watch_org": "Tencent Hunyuan",
    "full_name": "Tencent-Hunyuan/HY-SOAR",
    "html_url": "https://github.com/Tencent-Hunyuan/HY-SOAR",
    "stargazers_count": 631,
    "updated_at": "2026-06-12T14:46:44Z",
    "why": "recent update in watched organization `Tencent Hunyuan`"
  },
  {
    "watch_org": "Tencent Hunyuan",
    "full_name": "Tencent-Hunyuan/HunyuanCustom",
    "html_url": "https://github.com/Tencent-Hunyuan/HunyuanCustom",
    "stargazers_count": 1225,
    "updated_at": "2026-06-12T06:43:35Z",
    "why": "recent update in watched organization `Tencent Hunyuan`"
  },
  {
    "watch_org": "Tencent Hunyuan",
    "full_name": "Tencent-Hunyuan/Hunyuan3D-Part",
    "html_url": "https://github.com/Tencent-Hunyuan/Hunyuan3D-Part",
    "stargazers_count": 495,
    "updated_at": "2026-06-12T03:58:55Z",
    "why": "recent update in watched organization `Tencent Hunyuan`"
  },
  {
    "watch_org": "Tencent Hunyuan",
    "full_name": "Tencent-Hunyuan/SRPO",
    "html_url": "https://github.com/Tencent-Hunyuan/SRPO",
    "stargazers_count": 1275,
    "updated_at": "2026-06-11T14:39:43Z",
    "why": "recent update in watched organization `Tencent Hunyuan`"
  },
  {
    "watch_org": "Tencent Hunyuan",
    "full_name": "Tencent-Hunyuan/Hunyuan3D-1",
    "html_url": "https://github.com/Tencent-Hunyuan/Hunyuan3D-1",
    "stargazers_count": 3475,
    "updated_at": "2026-06-11T11:52:30Z",
    "why": "recent update in watched organization `Tencent Hunyuan`"
  },
  {
    "watch_org": "Tencent Hunyuan",
    "full_name": "Tencent-Hunyuan/HunyuanImage-2.1",
    "html_url": "https://github.com/Tencent-Hunyuan/HunyuanImage-2.1",
    "stargazers_count": 672,
    "updated_at": "2026-06-11T11:25:15Z",
    "why": "recent update in watched organization `Tencent Hunyuan`"
  },
  {
    "watch_org": "Tencent Hunyuan",
    "full_name": "Tencent-Hunyuan/HY3D-Bench",
    "html_url": "https://github.com/Tencent-Hunyuan/HY3D-Bench",
    "stargazers_count": 341,
    "updated_at": "2026-06-09T21:10:37Z",
    "why": "recent update in watched organization `Tencent Hunyuan`"
  },
  {
    "watch_org": "Tencent Hunyuan",
    "full_name": "Tencent-Hunyuan/R-DMesh",
    "html_url": "https://github.com/Tencent-Hunyuan/R-DMesh",
    "stargazers_count": 37,
    "updated_at": "2026-06-07T10:41:27Z",
    "why": "recent update in watched organization `Tencent Hunyuan`"
  },
  {
    "watch_org": "Tencent Hunyuan",
    "full_name": "Tencent-Hunyuan/Hunyuan-GameCraft-1.0",
    "html_url": "https://github.com/Tencent-Hunyuan/Hunyuan-GameCraft-1.0",
    "stargazers_count": 723,
    "updated_at": "2026-06-04T09:45:45Z",
    "why": "recent update in watched organization `Tencent Hunyuan`"
  },
  {
    "watch_org": "Tencent ARC",
    "full_name": "TencentARC/Pixal3D",
    "html_url": "https://github.com/TencentARC/Pixal3D",
    "stargazers_count": 1758,
    "updated_at": "2026-06-15T06:28:41Z",
    "why": "recent update in watched organization `Tencent ARC`"
  },
  {
    "watch_org": "Tencent ARC",
    "full_name": "TencentARC/RollingForcing",
    "html_url": "https://github.com/TencentARC/RollingForcing",
    "stargazers_count": 413,
    "updated_at": "2026-06-15T05:28:47Z",
    "why": "recent update in watched organization `Tencent ARC`"
  },
  {
    "watch_org": "Tencent ARC",
    "full_name": "TencentARC/Sculpt4D",
    "html_url": "https://github.com/TencentARC/Sculpt4D",
    "stargazers_count": 4,
    "updated_at": "2026-06-14T05:12:29Z",
    "why": "recent update in watched organization `Tencent ARC`"
  },
  {
    "watch_org": "Tencent ARC",
    "full_name": "TencentARC/BrushNet",
    "html_url": "https://github.com/TencentARC/BrushNet",
    "stargazers_count": 1737,
    "updated_at": "2026-06-13T06:38:06Z",
    "why": "recent update in watched organization `Tencent ARC`"
  },
  {
    "watch_org": "Tencent ARC",
    "full_name": "TencentARC/AnimeGamer",
    "html_url": "https://github.com/TencentARC/AnimeGamer",
    "stargazers_count": 347,
    "updated_at": "2026-06-12T07:23:44Z",
    "why": "recent update in watched organization `Tencent ARC`"
  },
  {
    "watch_org": "Tencent ARC",
    "full_name": "TencentARC/StereoCrafter",
    "html_url": "https://github.com/TencentARC/StereoCrafter",
    "stargazers_count": 490,
    "updated_at": "2026-06-12T07:08:07Z",
    "why": "recent update in watched organization `Tencent ARC`"
  },
  {
    "watch_org": "Tencent ARC",
    "full_name": "TencentARC/MotionCrafter",
    "html_url": "https://github.com/TencentARC/MotionCrafter",
    "stargazers_count": 169,
    "updated_at": "2026-06-11T14:25:23Z",
    "why": "recent update in watched organization `Tencent ARC`"
  },
  {
    "watch_org": "Tencent ARC",
    "full_name": "TencentARC/T2I-Adapter",
    "html_url": "https://github.com/TencentARC/T2I-Adapter",
    "stargazers_count": 3802,
    "updated_at": "2026-06-11T11:51:49Z",
    "why": "recent update in watched organization `Tencent ARC`"
  },
  {
    "watch_org": "Tencent ARC",
    "full_name": "TencentARC/GenCompositor",
    "html_url": "https://github.com/TencentARC/GenCompositor",
    "stargazers_count": 158,
    "updated_at": "2026-06-11T00:39:55Z",
    "why": "recent update in watched organization `Tencent ARC`"
  },
  {
    "watch_org": "Tencent ARC",
    "full_name": "TencentARC/CubeComposer",
    "html_url": "https://github.com/TencentARC/CubeComposer",
    "stargazers_count": 123,
    "updated_at": "2026-06-10T22:15:41Z",
    "why": "recent update in watched organization `Tencent ARC`"
  },
  {
    "watch_org": "Tencent ARC",
    "full_name": "TencentARC/FreeSplatter",
    "html_url": "https://github.com/TencentARC/FreeSplatter",
    "stargazers_count": 241,
    "updated_at": "2026-06-10T06:17:24Z",
    "why": "recent update in watched organization `Tencent ARC`"
  },
  {
    "watch_org": "Tencent ARC",
    "full_name": "TencentARC/Track4World",
    "html_url": "https://github.com/TencentARC/Track4World",
    "stargazers_count": 234,
    "updated_at": "2026-06-10T03:13:52Z",
    "why": "recent update in watched organization `Tencent ARC`"
  },
  {
    "watch_org": "Tencent ARC",
    "full_name": "TencentARC/VerseCrafter",
    "html_url": "https://github.com/TencentARC/VerseCrafter",
    "stargazers_count": 398,
    "updated_at": "2026-06-09T12:18:26Z",
    "why": "recent update in watched organization `Tencent ARC`"
  },
  {
    "watch_org": "Tencent ARC",
    "full_name": "TencentARC/AudioStory",
    "html_url": "https://github.com/TencentARC/AudioStory",
    "stargazers_count": 302,
    "updated_at": "2026-06-02T17:20:27Z",
    "why": "recent update in watched organization `Tencent ARC`"
  },
  {
    "watch_org": "Tencent ARC",
    "full_name": "TencentARC/BrushEdit",
    "html_url": "https://github.com/TencentARC/BrushEdit",
    "stargazers_count": 588,
    "updated_at": "2026-06-02T17:19:54Z",
    "why": "recent update in watched organization `Tencent ARC`"
  },
  {
    "watch_org": "Tencent ARC",
    "full_name": "TencentARC/IC-Custom",
    "html_url": "https://github.com/TencentARC/IC-Custom",
    "stargazers_count": 161,
    "updated_at": "2026-06-02T03:11:14Z",
    "why": "recent update in watched organization `Tencent ARC`"
  },
  {
    "watch_org": "Alibaba",
    "full_name": "QwenLM/WebWorld",
    "html_url": "https://github.com/QwenLM/WebWorld",
    "stargazers_count": 39,
    "updated_at": "2026-06-09T18:31:58Z",
    "why": "recent update in watched organization `Alibaba`"
  },
  {
    "watch_org": "Alibaba VILab",
    "full_name": "ali-vilab/DiffusionOPD",
    "html_url": "https://github.com/ali-vilab/DiffusionOPD",
    "stargazers_count": 99,
    "updated_at": "2026-06-15T04:06:45Z",
    "why": "recent update in watched organization `Alibaba VILab`"
  },
  {
    "watch_org": "Alibaba VILab",
    "full_name": "ali-vilab/TeaCache",
    "html_url": "https://github.com/ali-vilab/TeaCache",
    "stargazers_count": 1339,
    "updated_at": "2026-06-14T03:57:09Z",
    "why": "recent update in watched organization `Alibaba VILab`"
  },
  {
    "watch_org": "Alibaba VILab",
    "full_name": "ali-vilab/Wan-Move",
    "html_url": "https://github.com/ali-vilab/Wan-Move",
    "stargazers_count": 632,
    "updated_at": "2026-06-14T01:59:04Z",
    "why": "recent update in watched organization `Alibaba VILab`"
  },
  {
    "watch_org": "Alibaba VILab",
    "full_name": "ali-vilab/In-Context-LoRA",
    "html_url": "https://github.com/ali-vilab/In-Context-LoRA",
    "stargazers_count": 2077,
    "updated_at": "2026-06-12T11:25:55Z",
    "why": "recent update in watched organization `Alibaba VILab`"
  },
  {
    "watch_org": "Alibaba VILab",
    "full_name": "ali-vilab/dreamtalk",
    "html_url": "https://github.com/ali-vilab/dreamtalk",
    "stargazers_count": 1792,
    "updated_at": "2026-06-11T11:48:11Z",
    "why": "recent update in watched organization `Alibaba VILab`"
  },
  {
    "watch_org": "Alibaba VILab",
    "full_name": "ali-vilab/MSAVBench",
    "html_url": "https://github.com/ali-vilab/MSAVBench",
    "stargazers_count": 1,
    "updated_at": "2026-06-09T09:29:45Z",
    "why": "recent update in watched organization `Alibaba VILab`"
  },
  {
    "watch_org": "Alibaba VILab",
    "full_name": "ali-vilab/Infusion",
    "html_url": "https://github.com/ali-vilab/Infusion",
    "stargazers_count": 556,
    "updated_at": "2026-06-05T17:17:24Z",
    "why": "recent update in watched organization `Alibaba VILab`"
  },
  {
    "watch_org": "Alibaba VILab",
    "full_name": "ali-vilab/videocomposer",
    "html_url": "https://github.com/ali-vilab/videocomposer",
    "stargazers_count": 956,
    "updated_at": "2026-06-04T03:19:20Z",
    "why": "recent update in watched organization `Alibaba VILab`"
  },
  {
    "watch_org": "Alibaba VILab",
    "full_name": "ali-vilab/CDT",
    "html_url": "https://github.com/ali-vilab/CDT",
    "stargazers_count": 15,
    "updated_at": "2026-06-03T07:19:51Z",
    "why": "recent update in watched organization `Alibaba VILab`"
  },
  {
    "watch_org": "ByteDance Seed",
    "full_name": "ByteDance-Seed/SeedVR",
    "html_url": "https://github.com/ByteDance-Seed/SeedVR",
    "stargazers_count": 1232,
    "updated_at": "2026-06-15T01:52:30Z",
    "why": "recent update in watched organization `ByteDance Seed`"
  },
  {
    "watch_org": "ByteDance Seed",
    "full_name": "ByteDance-Seed/SimArt",
    "html_url": "https://github.com/ByteDance-Seed/SimArt",
    "stargazers_count": 5,
    "updated_at": "2026-06-12T05:56:47Z",
    "why": "recent update in watched organization `ByteDance Seed`"
  },
  {
    "watch_org": "ByteDance Seed",
    "full_name": "ByteDance-Seed/TraceAnything",
    "html_url": "https://github.com/ByteDance-Seed/TraceAnything",
    "stargazers_count": 538,
    "updated_at": "2026-06-10T08:09:33Z",
    "why": "recent update in watched organization `ByteDance Seed`"
  },
  {
    "watch_org": "ByteDance Seed",
    "full_name": "ByteDance-Seed/Stable-DiffCoder",
    "html_url": "https://github.com/ByteDance-Seed/Stable-DiffCoder",
    "stargazers_count": 84,
    "updated_at": "2026-06-06T01:25:21Z",
    "why": "recent update in watched organization `ByteDance Seed`"
  },
  {
    "watch_org": "Adobe Research",
    "full_name": "adobe-research/custom-diffusion",
    "html_url": "https://github.com/adobe-research/custom-diffusion",
    "stargazers_count": 1974,
    "updated_at": "2026-06-11T11:51:45Z",
    "why": "recent update in watched organization `Adobe Research`"
  },
  {
    "watch_org": "Adobe Research",
    "full_name": "adobe-research/SuperGaussian",
    "html_url": "https://github.com/adobe-research/SuperGaussian",
    "stargazers_count": 77,
    "updated_at": "2026-06-09T02:42:41Z",
    "why": "recent update in watched organization `Adobe Research`"
  },
  {
    "watch_org": "Black Forest Labs",
    "full_name": "black-forest-labs/flux2",
    "html_url": "https://github.com/black-forest-labs/flux2",
    "stargazers_count": 2401,
    "updated_at": "2026-06-15T03:34:47Z",
    "why": "recent update in watched organization `Black Forest Labs`"
  },
  {
    "watch_org": "Black Forest Labs",
    "full_name": "black-forest-labs/skills",
    "html_url": "https://github.com/black-forest-labs/skills",
    "stargazers_count": 77,
    "updated_at": "2026-06-15T01:31:54Z",
    "why": "recent update in watched organization `Black Forest Labs`"
  },
  {
    "watch_org": "Stability AI",
    "full_name": "Stability-AI/stable-fast-3d",
    "html_url": "https://github.com/Stability-AI/stable-fast-3d",
    "stargazers_count": 1714,
    "updated_at": "2026-06-15T06:16:38Z",
    "why": "recent update in watched organization `Stability AI`"
  },
  {
    "watch_org": "Stability AI",
    "full_name": "Stability-AI/StableStudio",
    "html_url": "https://github.com/Stability-AI/StableStudio",
    "stargazers_count": 9045,
    "updated_at": "2026-06-15T01:39:20Z",
    "why": "recent update in watched organization `Stability AI`"
  },
  {
    "watch_org": "Stability AI",
    "full_name": "Stability-AI/StableSwarmUI",
    "html_url": "https://github.com/Stability-AI/StableSwarmUI",
    "stargazers_count": 4928,
    "updated_at": "2026-06-13T23:03:57Z",
    "why": "recent update in watched organization `Stability AI`"
  },
  {
    "watch_org": "Stability AI",
    "full_name": "Stability-AI/rcm_old",
    "html_url": "https://github.com/Stability-AI/rcm_old",
    "stargazers_count": 0,
    "updated_at": "2026-06-11T12:45:33Z",
    "why": "recent update in watched organization `Stability AI`"
  },
  {
    "watch_org": "Stability AI",
    "full_name": "Stability-AI/ReLi3D",
    "html_url": "https://github.com/Stability-AI/ReLi3D",
    "stargazers_count": 62,
    "updated_at": "2026-06-11T12:45:30Z",
    "why": "recent update in watched organization `Stability AI`"
  },
  {
    "watch_org": "Stability AI",
    "full_name": "Stability-AI/stable-virtual-camera",
    "html_url": "https://github.com/Stability-AI/stable-virtual-camera",
    "stargazers_count": 1615,
    "updated_at": "2026-06-11T12:45:25Z",
    "why": "recent update in watched organization `Stability AI`"
  },
  {
    "watch_org": "Stability AI",
    "full_name": "Stability-AI/stable-point-aware-3d",
    "html_url": "https://github.com/Stability-AI/stable-point-aware-3d",
    "stargazers_count": 1047,
    "updated_at": "2026-06-11T12:45:24Z",
    "why": "recent update in watched organization `Stability AI`"
  },
  {
    "watch_org": "Stability AI",
    "full_name": "Stability-AI/stability-ai-toolkit",
    "html_url": "https://github.com/Stability-AI/stability-ai-toolkit",
    "stargazers_count": 15,
    "updated_at": "2026-06-11T12:45:23Z",
    "why": "recent update in watched organization `Stability AI`"
  },
  {
    "watch_org": "Stability AI",
    "full_name": "Stability-AI/stable-3d-gallery",
    "html_url": "https://github.com/Stability-AI/stable-3d-gallery",
    "stargazers_count": 2,
    "updated_at": "2026-06-11T12:44:59Z",
    "why": "recent update in watched organization `Stability AI`"
  },
  {
    "watch_org": "Stability AI",
    "full_name": "Stability-AI/stable-dreamfusion-multiview",
    "html_url": "https://github.com/Stability-AI/stable-dreamfusion-multiview",
    "stargazers_count": 22,
    "updated_at": "2026-06-11T12:44:48Z",
    "why": "recent update in watched organization `Stability AI`"
  },
  {
    "watch_org": "Stability AI",
    "full_name": "Stability-AI/lora_accelerated",
    "html_url": "https://github.com/Stability-AI/lora_accelerated",
    "stargazers_count": 15,
    "updated_at": "2026-06-11T12:44:46Z",
    "why": "recent update in watched organization `Stability AI`"
  },
  {
    "watch_org": "Stability AI",
    "full_name": "Stability-AI/k-diffusion",
    "html_url": "https://github.com/Stability-AI/k-diffusion",
    "stargazers_count": 18,
    "updated_at": "2026-06-11T12:44:42Z",
    "why": "recent update in watched organization `Stability AI`"
  },
  {
    "watch_org": "Stability AI",
    "full_name": "Stability-AI/stability-sdk",
    "html_url": "https://github.com/Stability-AI/stability-sdk",
    "stargazers_count": 2437,
    "updated_at": "2026-06-11T12:44:41Z",
    "why": "recent update in watched organization `Stability AI`"
  },
  {
    "watch_org": "Stability AI",
    "full_name": "Stability-AI/diffusers",
    "html_url": "https://github.com/Stability-AI/diffusers",
    "stargazers_count": 179,
    "updated_at": "2026-06-11T12:44:41Z",
    "why": "recent update in watched organization `Stability AI`"
  }
]
